LICENSE
MANIFEST.in
README.rst
requirements.txt
setup.cfg
setup.py
TravisPy.egg-info/PKG-INFO
TravisPy.egg-info/SOURCES.txt
TravisPy.egg-info/dependency_links.txt
TravisPy.egg-info/requires.txt
TravisPy.egg-info/top_level.txt
travispy/__init__.py
travispy/_helpers.py
travispy/conftest.py
travispy/errors.py
travispy/travispy.py
travispy/entities/__init__.py
travispy/entities/_entity.py
travispy/entities/_restartable.py
travispy/entities/_stateful.py
travispy/entities/account.py
travispy/entities/branch.py
travispy/entities/broadcast.py
travispy/entities/build.py
travispy/entities/commit.py
travispy/entities/hook.py
travispy/entities/job.py
travispy/entities/log.py
travispy/entities/repo.py
travispy/entities/session.py
travispy/entities/user.py