Metadata-Version: 1.1
Name: TravisPy
Version: 0.3.5
Summary: Python API for Travis CI.
Home-page: https://github.com/menegazzo/travispy
Author: Fabio Menegazzo
Author-email: menegazzo@gmail.com
License: GPL
Keywords: travis ci continuous integration travisci
Platform: UNKNOWN
Classifier: Development Status :: 3 - Alpha
Classifier: License :: OSI Approved :: GNU General Public License v3 (GPLv3)
Classifier: Operating System :: OS Independent
Classifier: Programming Language :: Python :: 2.7
Classifier: Programming Language :: Python :: 3.4
Classifier: Programming Language :: Python :: 3.5
Classifier: Programming Language :: Python :: Implementation :: PyPy
